neodjango/utils.py
neodjango/__init__.py
neodjango/tests/test_env.py
neodjango/tests/test_settings.py
neodjango/tests/__init__.py
neodjango/db/__init__.py
neodjango/db/models/manager.py
neodjango/db/models/base.py
neodjango/db/models/options.py
neodjango/db/models/query.py
neodjango/db/models/__init__.py
neodjango/management/__init__.py
neodjango/management/commands/neo4j.py
neodjango/management/commands/__init__.py
neodjango/core/connection.py
neodjango/core/cypher.py
neodjango/core/__init__.py
neodjango-0.0.8.dist-info/METADATA
neodjango-0.0.8.dist-info/WHEEL
neodjango-0.0.8.dist-info/DESCRIPTION.rst
neodjango-0.0.8.dist-info/top_level.txt
neodjango-0.0.8.dist-info/metadata.json
neodjango-0.0.8.dist-info/RECORD
neodjango-0.0.8.dist-info/pbr.json
